RailIN/CaptchaBreak.py
RailIN/RailIN.py
RailIN/__init__.py
RailIN/prettify.py
RailIN-0.2.1.dist-info/DESCRIPTION.rst
RailIN-0.2.1.dist-info/METADATA
RailIN-0.2.1.dist-info/RECORD
RailIN-0.2.1.dist-info/WHEEL
RailIN-0.2.1.dist-info/metadata.json
RailIN-0.2.1.dist-info/top_level.txt
