Metadata-Version: 2.0
Name: RailIN
Version: 0.2.1
Summary: Unofficial API for Indian Railways.
Home-page: https://github.com/ash2shukla/RailIN
Author: Ashish Shukla
Author-email: ash2shukla@gmail.com
License: MIT
Download-URL: https://github.com/ash2shukla/RailIN/archive/0.1.tar.gz
Keywords: Railways,API,IR,unofficial
Platform: UNKNOWN
Requires-Dist: bs4
Requires-Dist: pillow (==4.2.1)
Requires-Dist: pytesseract (==0.1.7)
Requires-Dist: requests (==2.18.1)
Requires-Dist: user-agent (==0.1.8)
